automateYT/__init__.py
automateYT/__main__.py
automateYT/exceptions.py
automateYT-1.0.0.dist-info/METADATA
automateYT-1.0.0.dist-info/WHEEL
automateYT-1.0.0.dist-info/top_level.txt
automateYT-1.0.0.dist-info/RECORD
