Metadata-Version: 2.1
Name: automateYT
Version: 1.0.0
Summary: automateYT is lightweight library that automates downloading of youtube videos, subtitles (if available) and playlist.
Home-page: https://github.com/umutambyi-gad/automateYT
Author: Umutambyi Gad
Author-email: umutambyig@gmail.com
License: MIT
Keywords: automate,youtube,download,download_playlist,download_subtitle,generate_watch_url_from_playlist
Platform: UNKNOWN
Classifier: License :: OSI Approved :: MIT License
Classifier: Programming Language :: Python :: 3.6
Classifier: Programming Language :: Python :: 3.7
Classifier: Programming Language :: Python :: 3.8
Classifier: Programming Language :: Python :: 3.9
Classifier: Programming Language :: Python
Requires-Python: >=3.6
Requires-Dist: pytube
